dhint/__init__.py
dhint/base/__init__.py
dhint/base/_meta.py
dhint/base/base_enum.py
dhint/base/collections.py
dhint/base/datamodel.py
dhint/base/descriptor.py
dhint/base/detamodel.py
dhint/collections.py
dhint/descriptors.py
dhint/function_types.py
dhint/functions.py
dhint/hints.py
dhint/json_encoder.py
dhint/protocols.py
dhint/subdescriptor.py
dhint/type_hint.py
dhint-0.0.9.dist-info/WHEEL
dhint-0.0.9.dist-info/METADATA
dhint-0.0.9.dist-info/RECORD
