Metadata-Version: 2.1
Name: dhint
Version: 0.0.9
Summary: 
Author: Daniel Arantes
Author-email: arantesdv@me.com
Requires-Python: >=3.9,<4.0
Classifier: Programming Language :: Python :: 3
Classifier: Programming Language :: Python :: 3.10
Classifier: Programming Language :: Python :: 3.9
Requires-Dist: Unidecode (>=1.3.6,<2.0.0)
Requires-Dist: typing-extensions (>=4.6.2,<5.0.0)
